libspn_keras/__init__.py
libspn_keras/config/__init__.py
libspn_keras/config/accumulator_initializer.py
libspn_keras/config/linear_accumulator_constraint.py
libspn_keras/config/logspace_accumulator_constraint.py
libspn_keras/config/sum_op.py
libspn_keras/constraints/__init__.py
libspn_keras/constraints/clip.py
libspn_keras/constraints/greater_equal_epsilon.py
libspn_keras/constraints/greater_equal_epsilon_normalized.py
libspn_keras/constraints/log_normalized.py
libspn_keras/initializers/__init__.py
libspn_keras/initializers/dirichlet.py
libspn_keras/initializers/epsilon_inverse_fan_in.py
libspn_keras/initializers/equidistant.py
libspn_keras/initializers/kmeans.py
libspn_keras/initializers/poon_domingos.py
libspn_keras/layers/__init__.py
libspn_keras/layers/base_leaf.py
libspn_keras/layers/conv2d_product.py
libspn_keras/layers/conv2d_sum.py
libspn_keras/layers/dense_product.py
libspn_keras/layers/dense_sum.py
libspn_keras/layers/flat_to_regions.py
libspn_keras/layers/indicator_leaf.py
libspn_keras/layers/local2d_sum.py
libspn_keras/layers/location_scale_leaf.py
libspn_keras/layers/log_dropout.py
libspn_keras/layers/normalize_standard_score.py
libspn_keras/layers/permute_and_pad_scopes.py
libspn_keras/layers/permute_and_pad_scopes_random.py
libspn_keras/layers/reduce_product.py
libspn_keras/layers/root_sum.py
libspn_keras/layers/spatial_to_regions.py
libspn_keras/layers/temporal_dense_product.py
libspn_keras/layers/undecompose.py
libspn_keras/logspace.py
libspn_keras/losses/__init__.py
libspn_keras/losses/negative_log_joint.py
libspn_keras/losses/negative_log_likelihood.py
libspn_keras/math/__init__.py
libspn_keras/math/logconv.py
libspn_keras/math/logmatmul.py
libspn_keras/math/logutils.py
libspn_keras/math/soft_em_grads.py
libspn_keras/metrics/__init__.py
libspn_keras/metrics/log_joint.py
libspn_keras/metrics/log_likelihood.py
libspn_keras/models/__init__.py
libspn_keras/models/dynamic_spn.py
libspn_keras/models/sequential_spn.py
libspn_keras/models/spn.py
libspn_keras-0.6.0.dist-info/LICENSE
libspn_keras-0.6.0.dist-info/WHEEL
libspn_keras-0.6.0.dist-info/METADATA
libspn_keras-0.6.0.dist-info/RECORD
