Metadata-Version: 2.1
Name: libspn-keras
Version: 0.6.0
Summary: LibSPN-Keras: A fledxible and scalable library for layer-based building and training of Sum-Product Networks
Home-page: https://github.com/pronobis/libspn-keras
License: MIT
Keywords: Sum Product Networks,Probabilistic Deep Learning,TensorFlow,Uncertainty,Probabilistic Graphical Models
Author: Jos van de Wolfshaar
Author-email: jos.vandewolfshaar@gmail.com
Requires-Python: >=3.6.1
Classifier: Development Status :: 3 - Alpha
Classifier: Intended Audience :: Developers
Classifier: Intended Audience :: Education
Classifier: Intended Audience :: Science/Research
Classifier: License :: OSI Approved :: MIT License
Classifier: Programming Language :: Python :: 3
Classifier: Programming Language :: Python :: 3.7
Classifier: Programming Language :: Python :: 3.8
Classifier: Topic :: Scientific/Engineering :: Artificial Intelligence
Classifier: Topic :: Scientific/Engineering :: Image Processing
Classifier: Topic :: Software Development :: Libraries
Requires-Dist: colorlover
Requires-Dist: plotly
Requires-Dist: tensorflow (>=2.3)
Requires-Dist: tensorflow-probability (>=0.11)
Project-URL: Documentation, https://libspn-keras.readthedocs.io
Project-URL: Repository, https://github.com/pronobis/libspn-keras
